ml_functions/__init__.py
ml_functions/convolution2d.py
ml_functions/transpose2d.py
ml_functions/window1d.py
ml_functions-0.1.1.dist-info/METADATA
ml_functions-0.1.1.dist-info/WHEEL
ml_functions-0.1.1.dist-info/RECORD
