Metadata-Version: 2.1
Name: ml-functions
Version: 0.1.1
Summary: 
Author: Brian Farish
Author-email: brian.farish@gmail.com
Requires-Python: >=3.10,<3.13
Classifier: Programming Language :: Python :: 3
Classifier: Programming Language :: Python :: 3.10
Classifier: Programming Language :: Python :: 3.11
Requires-Dist: black (>=23.9.1,<24.0.0)
Requires-Dist: numpy (>=1.26.0,<2.0.0)
